gplume/API_Access.py
gplume/DateTimeMechanism.py
gplume/OpenWeatherMapAPI.py
gplume/__init__.py
gplume/gpm.py
gplume/inverse.py
gplume-1.0.2.dist-info/LICENSE
gplume-1.0.2.dist-info/METADATA
gplume-1.0.2.dist-info/WHEEL
gplume-1.0.2.dist-info/top_level.txt
gplume-1.0.2.dist-info/RECORD
