Metadata-Version: 2.1
Name: gplume
Version: 1.0.2
Summary: The Gaussian Plume Model for atmospheric dispersion and inverse modeling of contaminants with support for multiple sources and receptors.
Home-page: https://github.com/VaibhavVasdev/Gaussian-Plume_Model
Author: Vaibhav Vasdev
Author-email: vaibhavvasdev63@gmail.com
License: MIT
Keywords: GaussianPlumeModel
License-File: LICENSE
Requires-Dist: requests
Requires-Dist: numpy
Requires-Dist: scipy
Requires-Dist: python-dateutil
Requires-Dist: matplotlib
